LICENSE
MANIFEST.in
README.md
setup.py
multicall/__init__.py
multicall/balance_call.py
multicall/call.py
multicall/eth_decode.py
multicall/multicall.py
multicall/signature.py
multicall/__pycache__/__init__.cpython-312.pyc
multicall/__pycache__/balance_call.cpython-312.pyc
multicall/__pycache__/call.cpython-312.pyc
multicall/__pycache__/eth_decode.cpython-312.pyc
multicall/__pycache__/multicall.cpython-312.pyc
multicall/__pycache__/signature.cpython-312.pyc
multicall/service/__init__.py
multicall/service/base_token_service.py
multicall/service/erc1155_service.py
multicall/service/erc20_service.py
multicall/service/erc721_service.py
multicall/service/ether_service.py
multicall/service/token_service.py
multicall_py.egg-info/PKG-INFO
multicall_py.egg-info/SOURCES.txt
multicall_py.egg-info/dependency_links.txt
multicall_py.egg-info/requires.txt
multicall_py.egg-info/top_level.txt
tests/test_eth_decode.py
tests/test_signature.py